agi_med_utils/__init__.py
agi_med_utils/parallel_map.py
agi_med_utils/retries.py
agi_med_utils/trace_with.py
agi_med_utils/utils.py
agi_med_utils/utils_inspect.py
agi_med_utils/validators.py
agi_med_utils-3.0.3.dist-info/METADATA
agi_med_utils-3.0.3.dist-info/WHEEL
agi_med_utils-3.0.3.dist-info/top_level.txt
agi_med_utils-3.0.3.dist-info/RECORD
