Metadata-Version: 2.4
Name: agi_med_utils
Version: 3.0.3
Summary: Utilities for agi-med team
Author: AGI-MED-TEAM
Requires-Python: >=3.11
Requires-Dist: pydantic<=3.0.0,>=2.9.2
Requires-Dist: tqdm==4.67.*
